fastbktree-0.1.1.dist-info/METADATA
fastbktree-0.1.1.dist-info/WHEEL
fastbktree/__init__.py
fastbktree/fastbktree.cpython-311-darwin.so
fastbktree-0.1.1.dist-info/RECORD
