Metadata-Version: 2.4
Name: fastbktree
Version: 0.1.1
Classifier: Programming Language :: Rust
Classifier: Programming Language :: Python :: Implementation :: CPython
Classifier: Programming Language :: Python :: Implementation :: PyPy
Classifier: Programming Language :: Python :: 3
Classifier: Programming Language :: Python :: 3.8
Classifier: Programming Language :: Python :: 3.9
Classifier: Programming Language :: Python :: 3.10
Classifier: Programming Language :: Python :: 3.11
Classifier: Programming Language :: Python :: 3.12
Classifier: License :: OSI Approved :: MIT License
Classifier: Operating System :: OS Independent
Classifier: Topic :: Text Processing :: General
Classifier: Topic :: Software Development :: Libraries :: Python Modules
Summary: A Rust BK-tree implementation for fast fuzzy string matching in Python
Keywords: bktree,levenshtein,fuzzy-matching,string-matching,rust
Author-email: Amrit Rau <amritrau@users.noreply.github.com>
License: MIT
Requires-Python: >=3.8
